{
  "lastUpdated": "2026-06-09T05:17:23.330Z",
  "tools": [
    {
      "id": "https://www.producthunt.com/products/mai-image-2-3",
      "name": "Microsoft MAI-Voice-2",
      "description": "Discussion\n            |\n            Link",
      "link": "https://www.producthunt.com/r/p/1163789?app_id=339",
      "category": "Launches",
      "pricing": "Unknown",
      "access": "Direct Link",
      "date": "2026-06-04T21:38:54.000Z"
    },
    {
      "id": "https://www.producthunt.com/products/mai-image-2-5",
      "name": "MAI-Image-2.5",
      "description": "Discussion\n            |\n            Link",
      "link": "https://www.producthunt.com/r/p/1162954?app_id=339",
      "category": "Launches",
      "pricing": "Unknown",
      "access": "Direct Link",
      "date": "2026-06-04T03:20:01.000Z"
    },
    {
      "id": "https://www.producthunt.com/products/veltrix-ai",
      "name": "Veltrix AI",
      "description": "Discussion\n            |\n            Link",
      "link": "https://www.producthunt.com/r/p/1152327?app_id=339",
      "category": "Launches",
      "pricing": "Unknown",
      "access": "Direct Link",
      "date": "2026-05-21T08:17:52.000Z"
    },
    {
      "id": "https://www.producthunt.com/products/mailwarm",
      "name": "Mailwarm 2.0",
      "description": "Discussion\n            |\n            Link",
      "link": "https://www.producthunt.com/r/p/1144083?app_id=339",
      "category": "Launches",
      "pricing": "Unknown",
      "access": "Direct Link",
      "date": "2026-05-11T08:28:25.000Z"
    },
    {
      "id": "https://www.producthunt.com/products/extella-ai",
      "name": "Extella.AI",
      "description": "Discussion\n            |\n            Link",
      "link": "https://www.producthunt.com/r/p/1117728?app_id=339",
      "category": "Launches",
      "pricing": "Unknown",
      "access": "Direct Link",
      "date": "2026-04-07T11:12:18.000Z"
    }
  ]
}